polyswarmartifact/__init__.py
polyswarmartifact/artifact_type.py
polyswarmartifact/exceptions.py
polyswarmartifact/schema/__init__.py
polyswarmartifact/schema/assertion.py
polyswarmartifact/schema/bounty.py
polyswarmartifact/schema/schema.py
polyswarmartifact/schema/verdict.py
polyswarm_artifact-2.2.4.dist-info/LICENSE
polyswarm_artifact-2.2.4.dist-info/METADATA
polyswarm_artifact-2.2.4.dist-info/WHEEL
polyswarm_artifact-2.2.4.dist-info/top_level.txt
polyswarm_artifact-2.2.4.dist-info/RECORD
