Metadata-Version: 2.1
Name: polyswarm-artifact
Version: 2.2.4
Summary: Library containing artifact type enums and functions
Author-email: PolySwarm Developers <info@polyswarm.io>
License: MIT
Project-URL: Homepage, https://github.com/polyswarm/polyswarm-artifact
Project-URL: Repository, https://github.com/polyswarm/polyswarm-artifact
Classifier: Intended Audience :: Developers
Classifier: License :: OSI Approved :: MIT License
Classifier: Operating System :: OS Independent
Classifier: Programming Language :: Python :: 3.10
Classifier: Programming Language :: Python :: 3.11
Classifier: Programming Language :: Python :: 3.12
Requires-Python: <4,>=3.10
License-File: LICENSE
Requires-Dist: pydantic
Provides-Extra: tests
Requires-Dist: bump-my-version (~=1.2) ; extra == 'tests'
Requires-Dist: pytest ; extra == 'tests'
Requires-Dist: coverage ; extra == 'tests'
Requires-Dist: pytest-runner ; extra == 'tests'
Requires-Dist: pytest-cov ; extra == 'tests'
Requires-Dist: pytest-asyncio ; extra == 'tests'
Requires-Dist: pytest-timeout ; extra == 'tests'
